geak_eval/__init__.py
geak_eval/constants.py
geak_eval/initializations.py
geak_eval/run.py
geak_eval/run_old.py
geak_eval/data/__init__.py
geak_eval/data/ROCm/__init__.py
geak_eval/data/ROCm/data/__init__.py
geak_eval/data/ROCm/data/ROCm_v1/__init__.py
geak_eval/data/ROCm/data/ROCm_v1/gemm.py
geak_eval/data/ROCm/data/ROCm_v1/layernorm.py
geak_eval/data/ROCm/data/ROCm_v1/moe_gemm.py
geak_eval/data/ROCm/data/ROCm_v1/multreduce_matmul_dot_kernel.py
geak_eval/data/ROCm/data/ROCm_v1/naive_softmax.py
geak_eval/data/ROCm/data/ROCm_v1/rmsnorm_bwd.py
geak_eval/data/ROCm/data/ROCm_v1/rmsnorm_fwd.py
geak_eval/data/ROCm/data/ROCm_v1/softmax.py
geak_eval/data/ROCm/data/ROCm_v1/test_add_kernel.py
geak_eval/data/ROCm/data/ROCm_v1/test_batched_vecmat.py
geak_eval/data/ROCm/data/ROCm_v1/test_block_copy.py
geak_eval/data/ROCm/data/ROCm_v1/test_block_pointer_matmul.py
geak_eval/data/ROCm/data/ROCm_v1/test_cast_matmul.py
geak_eval/data/ROCm/data/ROCm_v1/test_chained_dot_fp8.py
geak_eval/data/ROCm/data/ROCm_v1/test_chained_matmul.py
geak_eval/data/ROCm/data/ROCm_v1/test_flashattention_fwd.py
geak_eval/data/ROCm/data/ROCm_v1/test_gemm_fusion.py
geak_eval/data/ROCm/data/ROCm_v1/test_gemm_no_scf.py
geak_eval/data/ROCm/data/ROCm_v1/test_iv_dependent_matmul.py
geak_eval/data/ROCm/data/ROCm_v1/test_kernel_dot.py
geak_eval/data/ROCm/data/ROCm_v1/test_kernel_sub.py
geak_eval/data/ROCm/data/ROCm_v1/test_load_reduce.py
geak_eval/data/ROCm/data/ROCm_v1/test_matmul_MXFP.py
geak_eval/data/ROCm/data/ROCm_v1/test_randn.py
geak_eval/data/ROCm/data/ROCm_v1/test_random_int.py
geak_eval/data/ROCm/data/ROCm_v1/test_reverse_range.py
geak_eval/data/ROCm/data/ROCm_v1/test_tma_store_gemm.py
geak_eval/data/ROCm/data/ROCm_v1/test_triton_flip.py
geak_eval/data/ROCm/data/ROCm_v1/test_triton_sort.py
geak_eval/data/ROCm/data/ROCm_v1/test_triton_swizzle2d.py
geak_eval/data/ROCm/data/ROCm_v1/triton_multreduce_matmul_kernel.py
geak_eval/data/TritonBench/__init__.py
geak_eval/data/TritonBench/data/__init__.py
geak_eval-0.1.5.dist-info/licenses/LICENSE.txt
geak_eval-0.1.5.dist-info/METADATA
geak_eval-0.1.5.dist-info/WHEEL
geak_eval-0.1.5.dist-info/entry_points.txt
geak_eval-0.1.5.dist-info/top_level.txt
geak_eval-0.1.5.dist-info/RECORD
