Metadata-Version: 2.4
Name: geak-eval
Version: 0.1.5
Summary: An evaluation framework for Triton kernels
Author: Vinay Joshi
Author-email: vinajosh@amd.com
Classifier: Programming Language :: Python :: 3
Classifier: Operating System :: OS Independent
Requires-Python: >=3.7
License-File: LICENSE.txt
Requires-Dist: triton==3.3.0
Requires-Dist: parse_llm_code
Requires-Dist: pandas
Requires-Dist: numpy==1.26
Requires-Dist: openai==0.28
Dynamic: author
Dynamic: author-email
Dynamic: classifier
Dynamic: description
Dynamic: description-content-type
Dynamic: license-file
Dynamic: requires-dist
Dynamic: requires-python
Dynamic: summary
